{"assets/icons/.DS_Store":["assets/icons/.DS_Store"],"assets/icons/bg.svg":["assets/icons/bg.svg"],"assets/icons/clock.svg":["assets/icons/clock.svg"],"assets/icons/heydev_icon.jpeg":["assets/icons/heydev_icon.jpeg"],"assets/lotties/.DS_Store":["assets/lotties/.DS_Store"],"assets/lotties/404.json":["assets/lotties/404.json"],"assets/lotties/favicon_io.zip":["assets/lotties/favicon_io.zip"],"packages/cupertino_icons/assets/CupertinoIcons.ttf":["packages/cupertino_icons/assets/CupertinoIcons.ttf"]}